{
    "namespace": "0bf94102-e0e3-478b-ab0c-caa40f34a5d8",
    "name": "cache_exp_ibm",
    "version": "0.0.15",
    "subject": "188953187@qq.com",
    "activationId": "09927b336e4a4076927b336e4a107679",
    "start": 1659655314382,
    "end": 1659655540745,
    "duration": 226363,
    "statusCode": 0,
    "response": {
        "status": "success",
        "statusCode": 0,
        "success": true,
        "result": {
            "architecture": "x86",
            "cache_bench_metric": "\n\t\tdouble Write Cache Test\n\nC Size\t\tNanosec\t\tMB/sec\t\t% Chnge\n-------\t\t-------\t\t-------\t\t-------\n256             0.75            10189.38        1.00           \n384             0.86            8890.91         1.15           \n512             0.73            10492.18        0.85           \n768             0.99            7693.41         1.36           \n1024            0.84            9042.31         0.85           \n1536            0.75            10110.57        0.89           \n2048            0.87            8779.52         1.15           \n3072            0.72            10634.37        0.83           \n4096            0.84            9048.16         1.18           \n6144            0.86            8822.80         1.03           \n8192            0.80            9520.94         0.93           \n12288           0.79            9643.78         0.99           \n16384           0.86            8909.81         1.08           \n24576           0.77            9870.86         0.90           \n32768           0.80            9511.60         1.04           \n49152           0.96            7920.96         1.20           \n65536           0.77            9954.82         0.80           \n98304           0.84            9086.08         1.10           \n131072          0.87            8803.79         1.03           \n196608          0.93            8224.75         1.07           \n262144          0.77            9879.63         0.83           \n393216          0.75            10154.99        0.97           \n524288          0.92            8287.91         1.23           \n786432          0.76            10073.12        0.82           \n1048576         0.83            9143.91         1.10           \n1572864         0.81            9367.62         0.98           \n2097152         0.75            10137.62        0.92           \n3145728         0.78            9818.35         1.03           \n4194304         0.72            10580.02        0.93           \n6291456         0.75            10238.89        1.03           \n8388608         1.03            7374.99         1.39           \n12582912        0.94            8142.41         0.91           \n16777216        0.92            8317.27         0.98           \n25165824        1.10            6961.46         1.19           \n33554432        1.28            5980.68         1.16           \n50331648        1.47            5202.92         1.15           \n67108864        1.32            5759.90         0.90           \n100663296       1.45            5272.49         1.09           \n134217728       1.36            5618.29         0.94           \n201326592       1.38            5537.24         1.01           \n268435456       1.39            5506.43         1.01           \n402653184       1.49            5128.00         1.07           \n536870912       1.44            5307.67         0.97           \n805306368       1.45            5267.86         1.01           \n1073741824      1.45            5259.29         1.00           \n",
            "cpuCores": 4,
            "cpuGuest": 0.0,
            "cpuGuestDelta": 0.0,
            "cpuGuestNice": 0.0,
            "cpuGuestNiceDelta": 0.0,
            "cpuIOWait": 278730.0,
            "cpuIOWaitDelta": 390.0,
            "cpuIdle": 499762830.0,
            "cpuIdleDelta": 406280.0,
            "cpuInfo": [
                {
                    "address_sizes": "46 bits physical, 48 bits virtual",
                    "apicid": "0",
                    "bogomips": "4788.75",
                    "bugs": [
                        "cpu_meltdown",
                        "spectre_v1",
                        "spectre_v2",
                        "spec_store_bypass",
                        "l1tf",
                        "mds",
                        "swapgs",
                        "itlb_multihit",
                        "mmio_stale_data"
                    ],
                    "cache_alignment": "64",
                    "cache_size": "36608 KB",
                    "clflush_size": "64",
                    "core_id": "0",
                    "cpu_MHz": "2394.298",
                    "cpu_cores": "4",
                    "cpu_family": "6",
                    "cpuid_level": "13",
                    "flags": [
                        "fpu",
                        "vme",
                        "de",
                        "pse",
                        "tsc",
                        "msr",
                        "pae",
                        "mce",
                        "cx8",
                        "apic",
                        "sep",
                        "mtrr",
                        "pge",
                        "mca",
                        "cmov",
                        "pat",
                        "pse36",
                        "clflush",
                        "acpi",
                        "mmx",
                        "fxsr",
                        "sse",
                        "sse2",
                        "ss",
                        "ht",
                        "syscall",
                        "pdpe1gb",
                        "rdtscp",
                        "lm",
                        "constant_tsc",
                        "rep_good",
                        "nopl",
                        "cpuid",
                        "pni",
                        "pclmulqdq",
                        "ssse3",
                        "fma",
                        "cx16",
                        "pcid",
                        "sse4_1",
                        "sse4_2",
                        "x2apic",
                        "movbe",
                        "popcnt",
                        "tsc_deadline_timer",
                        "aes",
                        "xsave",
                        "avx",
                        "f16c",
                        "rdrand",
                        "hypervisor",
                        "lahf_lm",
                        "abm",
                        "3dnowprefetch",
                        "cpuid_fault",
                        "invpcid_single",
                        "pti",
                        "intel_ppin",
                        "ssbd",
                        "ibrs",
                        "ibpb",
                        "stibp",
                        "fsgsbase",
                        "tsc_adjust",
                        "bmi1",
                        "avx2",
                        "smep",
                        "bmi2",
                        "erms",
                        "invpcid",
                        "mpx",
                        "rdseed",
                        "adx",
                        "clflushopt",
                        "clwb",
                        "xsaveopt",
                        "xsavec",
                        "xgetbv1",
                        "xsaves",
                        "pku",
                        "ospke",
                        "md_clear",
                        "flush_l1d"
                    ],
                    "fpu": "yes",
                    "fpu_exception": "yes",
                    "initial_apicid": "0",
                    "microcode": "0x5003102",
                    "model": "85",
                    "model_name": "Intel(R) Xeon(R) Platinum 8260 CPU @ 2.40GHz",
                    "physical_id": "0",
                    "processor": "0",
                    "siblings": "4",
                    "stepping": "7",
                    "vendor_id": "GenuineIntel",
                    "wp": "yes"
                },
                {
                    "address_sizes": "46 bits physical, 48 bits virtual",
                    "apicid": "2",
                    "bogomips": "4788.75",
                    "bugs": [
                        "cpu_meltdown",
                        "spectre_v1",
                        "spectre_v2",
                        "spec_store_bypass",
                        "l1tf",
                        "mds",
                        "swapgs",
                        "itlb_multihit",
                        "mmio_stale_data"
                    ],
                    "cache_alignment": "64",
                    "cache_size": "36608 KB",
                    "clflush_size": "64",
                    "core_id": "2",
                    "cpu_MHz": "2394.298",
                    "cpu_cores": "4",
                    "cpu_family": "6",
                    "cpuid_level": "13",
                    "flags": [
                        "fpu",
                        "vme",
                        "de",
                        "pse",
                        "tsc",
                        "msr",
                        "pae",
                        "mce",
                        "cx8",
                        "apic",
                        "sep",
                        "mtrr",
                        "pge",
                        "mca",
                        "cmov",
                        "pat",
                        "pse36",
                        "clflush",
                        "acpi",
                        "mmx",
                        "fxsr",
                        "sse",
                        "sse2",
                        "ss",
                        "ht",
                        "syscall",
                        "pdpe1gb",
                        "rdtscp",
                        "lm",
                        "constant_tsc",
                        "rep_good",
                        "nopl",
                        "cpuid",
                        "pni",
                        "pclmulqdq",
                        "ssse3",
                        "fma",
                        "cx16",
                        "pcid",
                        "sse4_1",
                        "sse4_2",
                        "x2apic",
                        "movbe",
                        "popcnt",
                        "tsc_deadline_timer",
                        "aes",
                        "xsave",
                        "avx",
                        "f16c",
                        "rdrand",
                        "hypervisor",
                        "lahf_lm",
                        "abm",
                        "3dnowprefetch",
                        "cpuid_fault",
                        "invpcid_single",
                        "pti",
                        "intel_ppin",
                        "ssbd",
                        "ibrs",
                        "ibpb",
                        "stibp",
                        "fsgsbase",
                        "tsc_adjust",
                        "bmi1",
                        "avx2",
                        "smep",
                        "bmi2",
                        "erms",
                        "invpcid",
                        "mpx",
                        "rdseed",
                        "adx",
                        "clflushopt",
                        "clwb",
                        "xsaveopt",
                        "xsavec",
                        "xgetbv1",
                        "xsaves",
                        "pku",
                        "ospke",
                        "md_clear",
                        "flush_l1d"
                    ],
                    "fpu": "yes",
                    "fpu_exception": "yes",
                    "initial_apicid": "2",
                    "microcode": "0x5003102",
                    "model": "85",
                    "model_name": "Intel(R) Xeon(R) Platinum 8260 CPU @ 2.40GHz",
                    "physical_id": "0",
                    "processor": "1",
                    "siblings": "4",
                    "stepping": "7",
                    "vendor_id": "GenuineIntel",
                    "wp": "yes"
                },
                {
                    "address_sizes": "46 bits physical, 48 bits virtual",
                    "apicid": "4",
                    "bogomips": "4788.75",
                    "bugs": [
                        "cpu_meltdown",
                        "spectre_v1",
                        "spectre_v2",
                        "spec_store_bypass",
                        "l1tf",
                        "mds",
                        "swapgs",
                        "itlb_multihit",
                        "mmio_stale_data"
                    ],
                    "cache_alignment": "64",
                    "cache_size": "36608 KB",
                    "clflush_size": "64",
                    "core_id": "4",
                    "cpu_MHz": "2394.298",
                    "cpu_cores": "4",
                    "cpu_family": "6",
                    "cpuid_level": "13",
                    "flags": [
                        "fpu",
                        "vme",
                        "de",
                        "pse",
                        "tsc",
                        "msr",
                        "pae",
                        "mce",
                        "cx8",
                        "apic",
                        "sep",
                        "mtrr",
                        "pge",
                        "mca",
                        "cmov",
                        "pat",
                        "pse36",
                        "clflush",
                        "acpi",
                        "mmx",
                        "fxsr",
                        "sse",
                        "sse2",
                        "ss",
                        "ht",
                        "syscall",
                        "pdpe1gb",
                        "rdtscp",
                        "lm",
                        "constant_tsc",
                        "rep_good",
                        "nopl",
                        "cpuid",
                        "pni",
                        "pclmulqdq",
                        "ssse3",
                        "fma",
                        "cx16",
                        "pcid",
                        "sse4_1",
                        "sse4_2",
                        "x2apic",
                        "movbe",
                        "popcnt",
                        "tsc_deadline_timer",
                        "aes",
                        "xsave",
                        "avx",
                        "f16c",
                        "rdrand",
                        "hypervisor",
                        "lahf_lm",
                        "abm",
                        "3dnowprefetch",
                        "cpuid_fault",
                        "invpcid_single",
                        "pti",
                        "intel_ppin",
                        "ssbd",
                        "ibrs",
                        "ibpb",
                        "stibp",
                        "fsgsbase",
                        "tsc_adjust",
                        "bmi1",
                        "avx2",
                        "smep",
                        "bmi2",
                        "erms",
                        "invpcid",
                        "mpx",
                        "rdseed",
                        "adx",
                        "clflushopt",
                        "clwb",
                        "xsaveopt",
                        "xsavec",
                        "xgetbv1",
                        "xsaves",
                        "pku",
                        "ospke",
                        "md_clear",
                        "flush_l1d"
                    ],
                    "fpu": "yes",
                    "fpu_exception": "yes",
                    "initial_apicid": "4",
                    "microcode": "0x5003102",
                    "model": "85",
                    "model_name": "Intel(R) Xeon(R) Platinum 8260 CPU @ 2.40GHz",
                    "physical_id": "0",
                    "processor": "2",
                    "siblings": "4",
                    "stepping": "7",
                    "vendor_id": "GenuineIntel",
                    "wp": "yes"
                },
                {
                    "address_sizes": "46 bits physical, 48 bits virtual",
                    "apicid": "6",
                    "bogomips": "4788.75",
                    "bugs": [
                        "cpu_meltdown",
                        "spectre_v1",
                        "spectre_v2",
                        "spec_store_bypass",
                        "l1tf",
                        "mds",
                        "swapgs",
                        "itlb_multihit",
                        "mmio_stale_data"
                    ],
                    "cache_alignment": "64",
                    "cache_size": "36608 KB",
                    "clflush_size": "64",
                    "core_id": "6",
                    "cpu_MHz": "2394.298",
                    "cpu_cores": "4",
                    "cpu_family": "6",
                    "cpuid_level": "13",
                    "flags": [
                        "fpu",
                        "vme",
                        "de",
                        "pse",
                        "tsc",
                        "msr",
                        "pae",
                        "mce",
                        "cx8",
                        "apic",
                        "sep",
                        "mtrr",
                        "pge",
                        "mca",
                        "cmov",
                        "pat",
                        "pse36",
                        "clflush",
                        "acpi",
                        "mmx",
                        "fxsr",
                        "sse",
                        "sse2",
                        "ss",
                        "ht",
                        "syscall",
                        "pdpe1gb",
                        "rdtscp",
                        "lm",
                        "constant_tsc",
                        "rep_good",
                        "nopl",
                        "cpuid",
                        "pni",
                        "pclmulqdq",
                        "ssse3",
                        "fma",
                        "cx16",
                        "pcid",
                        "sse4_1",
                        "sse4_2",
                        "x2apic",
                        "movbe",
                        "popcnt",
                        "tsc_deadline_timer",
                        "aes",
                        "xsave",
                        "avx",
                        "f16c",
                        "rdrand",
                        "hypervisor",
                        "lahf_lm",
                        "abm",
                        "3dnowprefetch",
                        "cpuid_fault",
                        "invpcid_single",
                        "pti",
                        "intel_ppin",
                        "ssbd",
                        "ibrs",
                        "ibpb",
                        "stibp",
                        "fsgsbase",
                        "tsc_adjust",
                        "bmi1",
                        "avx2",
                        "smep",
                        "bmi2",
                        "erms",
                        "invpcid",
                        "mpx",
                        "rdseed",
                        "adx",
                        "clflushopt",
                        "clwb",
                        "xsaveopt",
                        "xsavec",
                        "xgetbv1",
                        "xsaves",
                        "pku",
                        "ospke",
                        "md_clear",
                        "flush_l1d"
                    ],
                    "fpu": "yes",
                    "fpu_exception": "yes",
                    "initial_apicid": "6",
                    "microcode": "0x5003102",
                    "model": "85",
                    "model_name": "Intel(R) Xeon(R) Platinum 8260 CPU @ 2.40GHz",
                    "physical_id": "0",
                    "processor": "3",
                    "siblings": "4",
                    "stepping": "7",
                    "vendor_id": "GenuineIntel",
                    "wp": "yes"
                }
            ],
            "cpuIrq": 0.0,
            "cpuIrqDelta": 0.0,
            "cpuKernel": 16688100.0,
            "cpuKernelDelta": 21330.0,
            "cpuModel": "85",
            "cpuNice": 11450.0,
            "cpuNiceDelta": 0.0,
            "cpuSoftIrq": 301180.0,
            "cpuSoftIrqDelta": 450.0,
            "cpuSteal": 4401520.0,
            "cpuStealDelta": 37420.0,
            "cpuType": "Intel(R) Xeon(R) Platinum 8260 CPU @ 2.40GHz",
            "cpuUser": 40754560.0,
            "cpuUserDelta": 469090.0,
            "endTime": 1659655540743,
            "frameworkRuntime": 13,
            "frameworkRuntimeDeltas": 0,
            "freeMemory": 5640616,
            "functionName": "/0bf94102-e0e3-478b-ab0c-caa40f34a5d8/cache_exp_ibm",
            "functionRegion": "https://us-east.functions.cloud.ibm.com",
            "initializationTime": 1659649913264,
            "invocations": 18,
            "lang": "python",
            "linuxVersion": "Linux action 4.15.0-189-generic #200-Ubuntu SMP Wed Jun 22 19:53:37 UTC 2022 x86_64 GNU/Linux",
            "newcontainer": 0,
            "pageFaults": 789851200,
            "pageFaultsDelta": 2160839,
            "platform": "IBM Cloud Functions",
            "runtime": 226359,
            "startTime": 1659655314384,
            "totalMemory": 16212368,
            "userRuntime": 226346,
            "uuid": "65cf393f-fc14-4144-844c-2b53c4a78635",
            "version": 0.6,
            "vmID": "fceef548-7472-c3b9-d3a6-1875fa41cb31",
            "vmcpusteal": 1659513021
        }
    },
    "logs": [],
    "annotations": [
        {
            "key": "path",
            "value": "0bf94102-e0e3-478b-ab0c-caa40f34a5d8/cache_exp_ibm"
        },
        {
            "key": "waitTime",
            "value": 57
        },
        {
            "key": "transId",
            "value": "7c4d4ba03252e29a1efa84248f4fbbb8"
        },
        {
            "key": "kind",
            "value": "blackbox"
        },
        {
            "key": "timeout",
            "value": false
        },
        {
            "key": "limits",
            "value": {
                "concurrency": 1,
                "logs": 10,
                "memory": 2048,
                "timeout": 600000
            }
        }
    ],
    "publish": false
}
